{"container":{"width":200,"height":200},"rectangles":[{"width":27,"height":54,"value":1},{"width":16,"height":109,"value":1},{"width":102,"height":37,"value":1},{"width":11,"height":33,"value":1},{"width":35,"height":76,"value":1},{"width":15,"height":46,"value":1},{"width":6,"height":41,"value":1},{"width":9,"height":14,"value":1},{"width":18,"height":27,"value":1},{"width":9,"height":60,"value":1},{"width":46,"height":35,"value":1},{"width":18,"height":56,"value":1},{"width":92,"height":22,"value":1},{"width":19,"height":45,"value":1},{"width":30,"height":5,"value":1},{"width":28,"height":20,"value":1},{"width":56,"height":36,"value":1},{"width":32,"height":15,"value":1},{"width":11,"height":30,"value":1},{"width":13,"height":17,"value":1},{"width":11,"height":18,"value":1},{"width":2,"height":5,"value":1},{"width":10,"height":13,"value":1},{"width":8,"height":22,"value":1},{"width":28,"height":55,"value":1},{"width":51,"height":16,"value":1},{"width":38,"height":71,"value":1},{"width":75,"height":51,"value":1},{"width":18,"height":40,"value":1},{"width":13,"height":32,"value":1},{"width":42,"height":7,"value":1},{"width":23,"height":27,"value":1},{"width":26,"height":5,"value":1},{"width":37,"height":50,"value":1},{"width":45,"height":12,"value":1},{"width":37,"height":11,"value":1},{"width":32,"height":37,"value":1},{"width":8,"height":10,"value":1},{"width":3,"height":17,"value":1},{"width":5,"height":22,"value":1},{"width":11,"height":25,"value":1},{"width":29,"height":7,"value":1},{"width":20,"height":31,"value":1},{"width":8,"height":19,"value":1},{"width":18,"height":32,"value":1},{"width":5,"height":25,"value":1},{"width":15,"height":12,"value":1},{"width":12,"height":31,"value":1},{"width":10,"height":36,"value":1}]}